zCurve/__init__.py
zCurve/zCurve.py
zCurve-0.0.4.dist-info/LICENSE
zCurve-0.0.4.dist-info/METADATA
zCurve-0.0.4.dist-info/WHEEL
zCurve-0.0.4.dist-info/top_level.txt
zCurve-0.0.4.dist-info/RECORD
