Metadata-Version: 2.1
Name: zCurve
Version: 0.0.4
Summary: zCurve maps multidimensional data to one dimension while preserving locality of the data points.
Home-page: https://github.com/rmrschub/pyMorton
Author: René Schubotz
Author-email: rene.schubotz@dfki.de
License: CC BY-NC-SA 4.0
Platform: UNKNOWN
